[{"line":1,"elements":[{"line":3,"name":"","description":"","type":"background","keyword":"Background","steps":[{"result":{"duration":4194800,"status":"skipped"},"line":5,"name":"Login","match":{"location":"StepsDefination.SearchTheProduct.Login()"},"after":[{"result":{"duration":1363100,"status":"skipped"},"match":{"location":"StepsDefination.Hook.addScreenshot(io.cucumber.java.Scenario)"}}],"keyword":"Given "}]},{"start_timestamp":"2024-06-23T07:16:02.247Z","before":[{"result":{"error_message":"org.openqa.selenium.TimeoutException: java.util.concurrent.TimeoutException\nBuild info: version: '4.18.1', revision: 'b1d3319b48'\nSystem info: os.name: 'Windows 11', os.arch: 'amd64', os.version: '10.0', java.version: '21.0.1'\nDriver info: org.openqa.selenium.chrome.ChromeDriver\nCommand: [f32457f9281fe0caf16683a246b9c66b, get {url=https://demo.nopcommerce.com/   }]\nCapabilities {acceptInsecureCerts: false, browserName: chrome, browserVersion: 126.0.6478.114, chrome: {chromedriverVersion: 126.0.6478.63 (df799988fdc9..., userDataDir: C:\\Users\\heman\\AppData\\Loca...}, fedcm:accounts: true, goog:chromeOptions: {debuggerAddress: localhost:51698}, networkConnectionEnabled: false, pageLoadStrategy: normal, platformName: windows, proxy: Proxy(), se:cdp: ws://localhost:51698/devtoo..., se:cdpVersion: 126.0.6478.114, setWindowRect: true, strictFileInteractability: false, timeouts: {implicit: 0, pageLoad: 300000, script: 30000}, unhandledPromptBehavior: dismiss and notify, webauthn:extension:credBlob: true, webauthn:extension:largeBlob: true, webauthn:extension:minPinLength: true, webauthn:extension:prf: true, webauthn:virtualAuthenticators: true}\nSession ID: f32457f9281fe0caf16683a246b9c66b\r\n\tat org.openqa.selenium.remote.http.jdk.JdkHttpClient.execute0(JdkHttpClient.java:403)\r\n\tat org.openqa.selenium.remote.http.AddSeleniumUserAgent.lambda$apply$0(AddSeleniumUserAgent.java:42)\r\n\tat org.openqa.selenium.remote.http.Filter.lambda$andFinally$1(Filter.java:55)\r\n\tat org.openqa.selenium.remote.http.jdk.JdkHttpClient.execute(JdkHttpClient.java:359)\r\n\tat org.openqa.selenium.remote.HttpCommandExecutor.execute(HttpCommandExecutor.java:187)\r\n\tat org.openqa.selenium.remote.service.DriverCommandExecutor.invokeExecute(DriverCommandExecutor.java:216)\r\n\tat org.openqa.selenium.remote.service.DriverCommandExecutor.execute(DriverCommandExecutor.java:174)\r\n\tat org.openqa.selenium.remote.RemoteWebDriver.execute(RemoteWebDriver.java:519)\r\n\tat org.openqa.selenium.remote.RemoteWebDriver.get(RemoteWebDriver.java:301)\r\n\tat StepsDefination.Hook.setup(Hook.java:26)\r\nCaused by: java.util.concurrent.TimeoutException\r\n\tat java.base/java.util.concurrent.CompletableFuture.timedGet(CompletableFuture.java:1960)\r\n\tat java.base/java.util.concurrent.CompletableFuture.get(CompletableFuture.java:2095)\r\n\tat org.openqa.selenium.remote.http.jdk.JdkHttpClient.execute0(JdkHttpClient.java:386)\r\n\tat org.openqa.selenium.remote.http.AddSeleniumUserAgent.lambda$apply$0(AddSeleniumUserAgent.java:42)\r\n\tat org.openqa.selenium.remote.http.Filter.lambda$andFinally$1(Filter.java:55)\r\n\tat org.openqa.selenium.remote.http.jdk.JdkHttpClient.execute(JdkHttpClient.java:359)\r\n\tat org.openqa.selenium.remote.HttpCommandExecutor.execute(HttpCommandExecutor.java:187)\r\n\tat org.openqa.selenium.remote.service.DriverCommandExecutor.invokeExecute(DriverCommandExecutor.java:216)\r\n\tat org.openqa.selenium.remote.service.DriverCommandExecutor.execute(DriverCommandExecutor.java:174)\r\n\tat org.openqa.selenium.remote.RemoteWebDriver.execute(RemoteWebDriver.java:519)\r\n\tat org.openqa.selenium.remote.RemoteWebDriver.get(RemoteWebDriver.java:301)\r\n\tat StepsDefination.Hook.setup(Hook.java:26)\r\n\tat java.base/jdk.internal.reflect.DirectMethodHandleAccessor.invoke(DirectMethodHandleAccessor.java:103)\r\n\tat java.base/java.lang.reflect.Method.invoke(Method.java:580)\r\n\tat io.cucumber.java.Invoker.doInvoke(Invoker.java:66)\r\n\tat io.cucumber.java.Invoker.invoke(Invoker.java:24)\r\n\tat io.cucumber.java.AbstractGlueDefinition.invokeMethod(AbstractGlueDefinition.java:47)\r\n\tat io.cucumber.java.JavaHookDefinition.execute(JavaHookDefinition.java:64)\r\n\tat io.cucumber.core.runner.CoreHookDefinition.execute(CoreHookDefinition.java:46)\r\n\tat io.cucumber.core.runner.HookDefinitionMatch.runStep(HookDefinitionMatch.java:21)\r\n\tat io.cucumber.core.runner.ExecutionMode$1.execute(ExecutionMode.java:10)\r\n\tat io.cucumber.core.runner.TestStep.executeStep(TestStep.java:81)\r\n\tat io.cucumber.core.runner.TestStep.run(TestStep.java:53)\r\n\tat io.cucumber.core.runner.TestCase.run(TestCase.java:78)\r\n\tat io.cucumber.core.runner.Runner.runPickle(Runner.java:75)\r\n\tat io.cucumber.junit.PickleRunners$NoStepDescriptions.lambda$run$0(PickleRunners.java:151)\r\n\tat io.cucumber.core.runtime.CucumberExecutionContext.lambda$runTestCase$5(CucumberExecutionContext.java:136)\r\n\tat io.cucumber.core.runtime.RethrowingThrowableCollector.executeAndThrow(RethrowingThrowableCollector.java:23)\r\n\tat io.cucumber.core.runtime.CucumberExecutionContext.runTestCase(CucumberExecutionContext.java:136)\r\n\tat io.cucumber.junit.PickleRunners$NoStepDescriptions.run(PickleRunners.java:148)\r\n\tat io.cucumber.junit.FeatureRunner.runChild(FeatureRunner.java:144)\r\n\tat io.cucumber.junit.FeatureRunner.runChild(FeatureRunner.java:28)\r\n\tat org.junit.runners.ParentRunner$4.run(ParentRunner.java:331)\r\n\tat org.junit.runners.ParentRunner$1.schedule(ParentRunner.java:79)\r\n\tat org.junit.runners.ParentRunner.runChildren(ParentRunner.java:329)\r\n\tat org.junit.runners.ParentRunner.access$100(ParentRunner.java:66)\r\n\tat org.junit.runners.ParentRunner$2.evaluate(ParentRunner.java:293)\r\n\tat org.junit.runners.ParentRunner$3.evaluate(ParentRunner.java:306)\r\n\tat org.junit.runners.ParentRunner.run(ParentRunner.java:413)\r\n\tat io.cucumber.junit.FeatureRunner.run(FeatureRunner.java:137)\r\n\tat io.cucumber.junit.Cucumber.runChild(Cucumber.java:196)\r\n\tat io.cucumber.junit.Cucumber.runChild(Cucumber.java:89)\r\n\tat org.junit.runners.ParentRunner$4.run(ParentRunner.java:331)\r\n\tat org.junit.runners.ParentRunner$1.schedule(ParentRunner.java:79)\r\n\tat org.junit.runners.ParentRunner.runChildren(ParentRunner.java:329)\r\n\tat org.junit.runners.ParentRunner.access$100(ParentRunner.java:66)\r\n\tat org.junit.runners.ParentRunner$2.evaluate(ParentRunner.java:293)\r\n\tat io.cucumber.core.runtime.CucumberExecutionContext.lambda$runFeatures$6(CucumberExecutionContext.java:147)\r\n\tat io.cucumber.core.runtime.CucumberExecutionContext.execute(CucumberExecutionContext.java:162)\r\n\tat io.cucumber.core.runtime.CucumberExecutionContext.runFeatures(CucumberExecutionContext.java:145)\r\n\tat io.cucumber.junit.Cucumber$StartAndFinishTestRun.evaluate(Cucumber.java:226)\r\n\tat org.junit.runners.ParentRunner$3.evaluate(ParentRunner.java:306)\r\n\tat org.junit.runners.ParentRunner.run(ParentRunner.java:413)\r\n\tat org.eclipse.jdt.internal.junit4.runner.JUnit4TestReference.run(JUnit4TestReference.java:93)\r\n\tat org.eclipse.jdt.internal.junit.runner.TestExecution.run(TestExecution.java:40)\r\n\tat org.eclipse.jdt.internal.junit.runner.RemoteTestRunner.runTests(RemoteTestRunner.java:529)\r\n\tat org.eclipse.jdt.internal.junit.runner.RemoteTestRunner.runTests(RemoteTestRunner.java:757)\r\n\tat org.eclipse.jdt.internal.junit.runner.RemoteTestRunner.run(RemoteTestRunner.java:452)\r\n\tat org.eclipse.jdt.internal.junit.runner.RemoteTestRunner.main(RemoteTestRunner.java:210)\r\n","duration":188739964500,"status":"failed"},"match":{"location":"StepsDefination.Hook.setup()"}}],"line":7,"name":"search and Add_to_cart","description":"","id":"order-the-product;search-and-add-to-cart","after":[{"result":{"duration":31041685800,"status":"passed"},"match":{"location":"StepsDefination.Hook.tearDown(io.cucumber.java.Scenario)"}}],"type":"scenario","keyword":"Scenario","steps":[{"result":{"duration":1330300,"status":"skipped"},"line":9,"name":"search and Add_to_cart the product","match":{"location":"StepsDefination.SearchTheProduct.search_and_add_to_cart_the_product()"},"after":[{"result":{"duration":1001200,"status":"skipped"},"match":{"location":"StepsDefination.Hook.addScreenshot(io.cucumber.java.Scenario)"}}],"keyword":"Given "},{"result":{"duration":999700,"status":"skipped"},"line":10,"name":"verify the Add_to_cart product","match":{"location":"StepsDefination.SearchTheProduct.verify_the_add_to_cart_product()"},"after":[{"result":{"duration":1304800,"status":"skipped"},"match":{"location":"StepsDefination.Hook.addScreenshot(io.cucumber.java.Scenario)"}}],"keyword":"When "},{"result":{"duration":1998700,"status":"skipped"},"line":11,"name":"checkout the product","match":{"location":"StepsDefination.SearchTheProduct.checkout_the_product()"},"after":[{"result":{"duration":996400,"status":"skipped"},"match":{"location":"StepsDefination.Hook.addScreenshot(io.cucumber.java.Scenario)"}}],"keyword":"And "},{"result":{"duration":1034200,"status":"skipped"},"line":12,"name":"Fill the address","match":{"location":"StepsDefination.SearchTheProduct.fill_the_address1()"},"after":[{"result":{"status":"skipped"},"match":{"location":"StepsDefination.Hook.addScreenshot(io.cucumber.java.Scenario)"}}],"keyword":"Then "},{"result":{"status":"skipped"},"line":13,"name":"verify the order","match":{"location":"StepsDefination.SearchTheProduct.verify_the_order()"},"after":[{"result":{"status":"skipped"},"match":{"location":"StepsDefination.Hook.addScreenshot(io.cucumber.java.Scenario)"}}],"keyword":"And "}]}],"name":"Order the product","description":"","id":"order-the-product","keyword":"Feature","uri":"file:FeaturesFiles/SearchAndOrder.feature","tags":[]}]